managed_readline_sessions.py
managed_readline_sessions-0.1.0a6.dist-info/licenses/LICENSE
managed_readline_sessions-0.1.0a6.dist-info/METADATA
managed_readline_sessions-0.1.0a6.dist-info/WHEEL
managed_readline_sessions-0.1.0a6.dist-info/top_level.txt
managed_readline_sessions-0.1.0a6.dist-info/RECORD
