Metadata-Version: 2.4
Name: managed-readline-sessions
Version: 0.1.0a6
Summary: A lightweight, Pythonic interface for building Python CLI tools with tab completion and command history.
Author-email: Jifeng Wu <jifengwu2k@gmail.com>
License-Expression: MIT
Project-URL: Homepage, https://github.com/jifengwu2k/managed-readline-sessions
Project-URL: Bug Tracker, https://github.com/jifengwu2k/managed-readline-sessions/issues
Classifier: Programming Language :: Python :: 2
Classifier: Programming Language :: Python :: 3
Classifier: Operating System :: OS Independent
Requires-Python: >=2
License-File: LICENSE
Requires-Dist: typing; python_version < "3.5"
Requires-Dist: pyreadline
Dynamic: license-file
